spacy_whisper/__init__.py
spacy_whisper/pipeline.py
spacy_whisper-0.0.1.dist-info/LICENSE
spacy_whisper-0.0.1.dist-info/METADATA
spacy_whisper-0.0.1.dist-info/WHEEL
spacy_whisper-0.0.1.dist-info/top_level.txt
spacy_whisper-0.0.1.dist-info/RECORD
