Metadata-Version: 2.1
Name: spacy-whisper
Version: 0.0.1
Summary: Integrate Whisper transcriptions with spaCy for advanced NLP tasks
Home-page: https://github.com/theirstory/spacy-whisper
Author: Their Story
License: MIT
Keywords: NLP,spaCy,Whisper,transcription
Classifier: Development Status :: 3 - Alpha
Classifier: Intended Audience :: Developers
Classifier: License :: OSI Approved :: MIT License
Classifier: Programming Language :: Python :: 3.10
Classifier: Topic :: Software Development :: Libraries :: Python Modules
Classifier: Topic :: Text Processing :: Linguistic
License-File: LICENSE
Requires-Dist: spacy (>=3.0)
